arepa/__init__.py
arepa/arepa.py
arepa-0.2.0.dist-info/DESCRIPTION.rst
arepa-0.2.0.dist-info/METADATA
arepa-0.2.0.dist-info/RECORD
arepa-0.2.0.dist-info/WHEEL
arepa-0.2.0.dist-info/metadata.json
arepa-0.2.0.dist-info/top_level.txt
