Metadata-Version: 2.0
Name: arepa
Version: 0.2.0
Summary: Arepa-making utility
Home-page: https://github.com/pydanny/arepa
Author: Daniel Roy Greenfeld
Author-email: pydanny@gmail.com
License: MIT license
Keywords: arepa
Platform: UNKNOWN
Classifier: Development Status :: 2 - Pre-Alpha
Classifier: Intended Audience :: Developers
Classifier: License :: OSI Approved :: MIT License
Classifier: Natural Language :: English
Classifier: Programming Language :: Python :: 3
Classifier: Programming Language :: Python :: 3.6
